swugenerator/__about__.py
swugenerator/__init__.py
swugenerator/artifact.py
swugenerator/generator.py
swugenerator/main.py
swugenerator/signer.py
swugenerator/swu_file.py
swugenerator/swu_sign.py
swugenerator-0.6.dist-info/licenses/LICENSE
swugenerator-0.6.dist-info/METADATA
swugenerator-0.6.dist-info/WHEEL
swugenerator-0.6.dist-info/entry_points.txt
swugenerator-0.6.dist-info/top_level.txt
swugenerator-0.6.dist-info/RECORD
