Metadata-Version: 2.4
Name: swugenerator
Version: 0.6
Summary: Generator of Update Packages (SWU) for SWUpdate OTA Agent
Home-page: https://github.com/sbabic/swugenerator
Author: Stefano Babic
Author-email: Stefano Babic <stefano.babic@swupdate.org>
License:                     GNU GENERAL PUBLIC LICENSE
Project-URL: Homepage, https://github.com/sbabic/swugenerator
Classifier: Programming Language :: Python :: 3
Classifier: Operating System :: OS Independent
Requires-Python: >=3.6
License-File: LICENSE
Requires-Dist: libconf~=2.0.1
Dynamic: author
Dynamic: home-page
Dynamic: license-file
Dynamic: requires-python
